src/macros.sv
/*
* Author:            Sorin Besleaga
* Last modification: 29.05.24
* Status:            finished
*/

//byte-addressable
`ifndef _macros_h
`define _macros_h
    //Phisical Address:
    `define WOFFSET 1:0   // word offset
    `define BOFFSET 5:2   // block offset
    `define INDEX   12:6  // index slice
    `define TAG     31:13 // tag slice

    //Cache defines:
    localparam BYTE      = 8;       // 1 B =  8 bits
    localparam SIZE      = (1<<18); // total size of cache data size in bits
    localparam NWAYS     = 4;       // number of set associetivity
    localparam NSETS     = 128;     // number of sets in cache
    localparam BLK_WIDTH = 512;     // size of the block in bits
    localparam PA_WIDTH  = 32;      // width of physical address and  in bits
    localparam WRD_WIDTH = 32;      // width of a word in bits


    localparam IDX_WIDTH = 7;       // 128 sets (1 set = 4 blocks)
    localparam TAG_WIDTH = 19;
    localparam BO_WIDTH  = 4;       // 16 words/block
    localparam WO_WIDTH  = 2;       // 4 B/word

`endif

src/mem.sv
`include "macros.sv"
//treb de definit aici operatiile pe memorie
//Un aray de byte-uri
module mem #(
    parameter DEPTH     = (1<<15),   // 32KB
    parameter WIDTH     = BYTE,
    parameter INIT      = 0,         // if 1, resets all the memory
    parameter SEED      = 1,
    parameter NSEED_BLK = 512
)
(
    input  wire                 clk,

    input  wire [PA_WIDTH-1:0]  addr,

    input  wire                 rd_en,
    input  wire                 wr_en,

    input  wire [BLK_WIDTH-1:0] wr_data,
    output reg  [BLK_WIDTH-1:0] rd_data
);

    reg [WIDTH-1:0] MM [0:DEPTH-1];
    integer i, j;

    initial begin 
        if(INIT)
        begin
            for(i = 0; i < DEPTH; i = i+1)
                MM[i] = {WIDTH{1'b0}};
        end
        
        if(SEED) 
        begin 
            for(i = 0; i < (BLK_WIDTH/BYTE)*NSEED_BLK; i = i+32'h40)
            begin 
                for (j = 0; j < (BLK_WIDTH/BYTE); j = j + 1) begin
                    MM[i+j] = {8'h0f + (i-j*i), 8'hf0 - (i*j+j)};
                    
                    //$display("MM[%d] = %h", i+j, MM[i+j]);
                end
            end

        end
    end


    // Calculate the number of words per block
    localparam WORDS_PER_BLOCK = BLK_WIDTH / WRD_WIDTH;
    localparam BYTES_PER_WORD = WRD_WIDTH / WIDTH;

    integer word_idx, byte_idx;

    // Read from Main Memory
    always @(*) begin
        if (rd_en) begin
            for (word_idx = 0; word_idx < WORDS_PER_BLOCK; word_idx = word_idx + 1) begin
                for (byte_idx = 0; byte_idx < BYTES_PER_WORD; byte_idx = byte_idx + 1) begin
                    rd_data[(word_idx * WRD_WIDTH) + (byte_idx * WIDTH) +: WIDTH] = MM[addr + (word_idx * BYTES_PER_WORD) + byte_idx];
                end
            end
            
        end
    end

    // Write to Main Memory
    always @(*) begin
        if (wr_en) begin
            for (word_idx = 0; word_idx < WORDS_PER_BLOCK; word_idx = word_idx + 1) begin
                for (byte_idx = 0; byte_idx < BYTES_PER_WORD; byte_idx = byte_idx + 1) begin
                    MM[addr + (word_idx * BYTES_PER_WORD) + byte_idx] = wr_data[(word_idx * WRD_WIDTH) + (byte_idx * WIDTH) +: WIDTH];
                    //$display("(addr: %d)(index_addr: %d) %h",addr,addr + (word_idx * BYTES_PER_WORD) + byte_idx, MM[addr + (word_idx * BYTES_PER_WORD) + byte_idx]);
                end
            end
            //$display("\n");
        end
    end

endmodule

src/cache_data.sv
/*
* Sorin Besleaga
* Last modified: 30.05.24
* Status: unfinished
*/

/*
* Specs:
*       Associativity level: 4   way
*       Cache data size:     32  KiB
*       Block size:          64  B/block
*       Number of sets:      128 sets
*       Word size:           4   B/word
*       Words per block:     16  words/block
*       Memory alignment:    Big-Endian
*/

`include "macros.sv"

module cache_data
(
    input  wire                  clk, rst_n,
    
    input  wire [PA_WIDTH-1:0]   addr,         // addr from CPU
    input  wire [WRD_WIDTH-1:0]  data_wr,      // data from CPU (store instruction) / data to write 
    
    input  wire                  rd_en,        // 1 if load instr
    input  wire                  wr_en,        // 1 if store instr
    
    //memory control outputs
    input  wire [BLK_WIDTH-1:0]  mem_rd_blk,
    output reg  [PA_WIDTH-1:0]   mem_addr,
    output reg                   mem_rd_en,
    output reg                   mem_wr_en,    // 1 if writing to memory
    output reg [BLK_WIDTH-1:0]   mem_wr_blk,   // data from cache to memory

    output reg                   hit,          // 1 if hit, 0 if miss
    output reg  [WRD_WIDTH-1:0]  word_out,     // data from cache to CPU
    output reg  [BYTE-1:0]       byte_out      // byte that is extracted from word
);

    // Define all ways
    reg                  valid [0:NWAYS-1][0:NSETS-1];
    reg                  dirty [0:NWAYS-1][0:NSETS-1];
    reg [1:0]            lru   [0:NWAYS-1][0:NSETS-1];
    reg [TAG_WIDTH-1:0]  tag   [0:NWAYS-1][0:NSETS-1];
    reg [BLK_WIDTH-1:0]  data  [0:NWAYS-1][0:NSETS-1];

    // Init to 0 all
    integer i, j;
    initial begin 
        for(i = 0; i < NWAYS; i = i + 1) 
        begin
            for(j = 0; j < NSETS; j = j + 1) 
            begin 
                valid[i][j] = 1'b0;
                dirty[i][j] = 1'b0;
                lru  [i][j] = 2'b00;
            end
        end
    end

    // always @* begin 
    //     for(i = 0; i < NWAYS; i = i + 1) 
    //     begin
    //         for(j = 0; j < NSETS; j = j + 1) 
    //         begin 
    //             $display("valid = %h dirty = %h lru = %h", valid[i][j], dirty[i][j], lru[i][j]);
    //         end
    //         $display("=======\n");
    //     end
    // end

    // start of actual FSM

    // state parameters
    localparam IDLE       = 3'b000;
    localparam RD_HIT     = 3'b001;
    localparam RD_MISS    = 3'b010;
    localparam WR_HIT     = 3'b011;
    localparam WR_MISS    = 3'b100;
    localparam EVICT      = 3'b101;
         
    // state registers
    reg[2:0] state, next;
    reg rd_m, wr_m;

    //change states
    always @(posedge clk, negedge rst_n) begin 
        if(!rst_n) state <= IDLE;
        else       state <= next;
    end

    // set next state
    always @(*) begin 
        next = state;
        case(state)
            IDLE : begin   
                if(~rd_en && ~wr_en)   next = IDLE;
                else if(rd_en && hit)  next = RD_HIT;
                else if(wr_en && hit)  next = WR_HIT;
                else if(rd_en && ~hit) 
                begin 
                                       next = EVICT;
                                       rd_m = 1'b1;
                                       wr_m = 1'b0;
                end
                else if(wr_en && ~hit)
                begin 
                                       next = EVICT;
                                       rd_m = 1'b0;
                                       wr_m = 1'b1;
                end
            end

            EVICT : begin
                    if(wr_m)           next = WR_MISS;
                    if(rd_m)           next = RD_MISS;
            end

            RD_MISS, 
            WR_MISS :                  next = IDLE;
        endcase
    end

    // trigger signals based on next state
    always @(posedge clk, negedge rst_n) 
    begin 
        case(next)
            IDLE: begin 
                hit <= ((valid[0][addr[`INDEX]] && (tag[0][addr[`INDEX]] == addr[`TAG]))
                      ||(valid[1][addr[`INDEX]] && (tag[1][addr[`INDEX]] == addr[`TAG]))
                      ||(valid[2][addr[`INDEX]] && (tag[2][addr[`INDEX]] == addr[`TAG]))
                      ||(valid[3][addr[`INDEX]] && (tag[3][addr[`INDEX]] == addr[`TAG])));

                mem_wr_en <= 1'b0;
                mem_rd_en <= 1'b0;
                word_out <= {WRD_WIDTH{1'bz}};
                byte_out <= {WRD_WIDTH{1'bz}};
                wr_m <= 1'b0;
                rd_m <= 1'b0;
            end

            RD_HIT: begin 
                if(valid[0][addr[`INDEX]] && (tag[0][addr[`INDEX]] == addr[`TAG])) 
                begin
                    word_out = data[0][addr[`INDEX]][(addr[`BOFFSET]*WRD_WIDTH)+:WRD_WIDTH];
                    byte_out = word_out[(addr[`WOFFSET]*BYTE) +: BYTE];

                    // update age registers
                    if(lru[1][addr[`INDEX]] <= lru[0][addr[`INDEX]]) lru[1][addr[`INDEX]] <= lru[1][addr[`INDEX]] + 1;
                    if(lru[2][addr[`INDEX]] <= lru[0][addr[`INDEX]]) lru[2][addr[`INDEX]] <= lru[2][addr[`INDEX]] + 1;
                    if(lru[3][addr[`INDEX]] <= lru[0][addr[`INDEX]]) lru[3][addr[`INDEX]] <= lru[3][addr[`INDEX]] + 1;
                    lru[0][addr[`INDEX]] = 2'b00;
                end

                else if(valid[1][addr[`INDEX]] && (tag[1][addr[`INDEX]] == addr[`TAG])) 
                begin
                    word_out = data[1][addr[`INDEX]][(addr[`BOFFSET]*WRD_WIDTH)+:WRD_WIDTH];
                    byte_out = word_out[(addr[`WOFFSET]*BYTE) +: BYTE];

                    // update age registers
                    if(lru[0][addr[`INDEX]] <= lru[1][addr[`INDEX]]) lru[0][addr[`INDEX]] <= lru[0][addr[`INDEX]] + 1;
                    if(lru[2][addr[`INDEX]] <= lru[1][addr[`INDEX]]) lru[2][addr[`INDEX]] <= lru[2][addr[`INDEX]] + 1;
                    if(lru[3][addr[`INDEX]] <= lru[1][addr[`INDEX]]) lru[3][addr[`INDEX]] <= lru[3][addr[`INDEX]] + 1;
                    lru[1][addr[`INDEX]] = 2'b00;
                end

                else if(valid[2][addr[`INDEX]] && (tag[2][addr[`INDEX]] == addr[`TAG])) 
                begin
                    word_out = data[2][addr[`INDEX]][(addr[`BOFFSET]*WRD_WIDTH)+:WRD_WIDTH];
                    byte_out = word_out[(addr[`WOFFSET]*BYTE) +: BYTE];

                    // update age registers
                    if(lru[1][addr[`INDEX]] <= lru[2][addr[`INDEX]]) lru[1][addr[`INDEX]] <= lru[1][addr[`INDEX]] + 1;
                    if(lru[0][addr[`INDEX]] <= lru[2][addr[`INDEX]]) lru[0][addr[`INDEX]] <= lru[0][addr[`INDEX]] + 1;
                    if(lru[3][addr[`INDEX]] <= lru[2][addr[`INDEX]]) lru[3][addr[`INDEX]] <= lru[3][addr[`INDEX]] + 1;
                    lru[2][addr[`INDEX]] = 2'b00;
                end

                else if(valid[3][addr[`INDEX]] && (tag[3][addr[`INDEX]] == addr[`TAG])) 
                begin
                    word_out = data[3][addr[`INDEX]][(addr[`BOFFSET]*WRD_WIDTH)+:WRD_WIDTH];
                    byte_out = word_out[(addr[`WOFFSET]*BYTE) +: BYTE];

                    // update age registers
                    if(lru[1][addr[`INDEX]] <= lru[3][addr[`INDEX]]) lru[1][addr[`INDEX]] <= lru[1][addr[`INDEX]] + 1;
                    if(lru[2][addr[`INDEX]] <= lru[3][addr[`INDEX]]) lru[2][addr[`INDEX]] <= lru[2][addr[`INDEX]] + 1;
                    if(lru[0][addr[`INDEX]] <= lru[3][addr[`INDEX]]) lru[0][addr[`INDEX]] <= lru[0][addr[`INDEX]] + 1;
                    lru[3][addr[`INDEX]] = 2'b00;
                end
            end

            WR_HIT : begin 
                 // i_th way
                if(valid[0][addr[`INDEX]] && (tag[0][addr[`INDEX]] == addr[`TAG])) 
                begin
                    // for store instr there is no output/byte word
                    word_out = {WRD_WIDTH{1'bz}};
                    byte_out = {BYTE{1'bz}};
                    // mark as dirty block
                    dirty[0][addr[`INDEX]] <= 1'b1;
                    // overwrite data info from cache's block
                    data[0][addr[`INDEX]][(addr[`BOFFSET]*WRD_WIDTH)+:WRD_WIDTH] <= data_wr;

                    // update age registers
                    if(lru[1][addr[`INDEX]] <= lru[0][addr[`INDEX]]) lru[1][addr[`INDEX]] <= lru[1][addr[`INDEX]] + 1;
                    if(lru[2][addr[`INDEX]] <= lru[0][addr[`INDEX]]) lru[2][addr[`INDEX]] <= lru[2][addr[`INDEX]] + 1;
                    if(lru[3][addr[`INDEX]] <= lru[0][addr[`INDEX]]) lru[3][addr[`INDEX]] <= lru[3][addr[`INDEX]] + 1;
                    lru[0][addr[`INDEX]] = 2'b00;
                end

                else if(valid[1][addr[`INDEX]] && (tag[1][addr[`INDEX]] == addr[`TAG])) 
                begin
                    word_out = {WRD_WIDTH{1'bz}};
                    byte_out = {BYTE{1'bz}};
                    dirty[1][addr[`INDEX]] <= 1'b1;
                    data[1][addr[`INDEX]][(addr[`BOFFSET]*WRD_WIDTH)+:WRD_WIDTH] <= data_wr;

                    // update age registers
                    if(lru[0][addr[`INDEX]] <= lru[1][addr[`INDEX]]) lru[0][addr[`INDEX]] <= lru[0][addr[`INDEX]] + 1;
                    if(lru[2][addr[`INDEX]] <= lru[1][addr[`INDEX]]) lru[2][addr[`INDEX]] <= lru[2][addr[`INDEX]] + 1;
                    if(lru[3][addr[`INDEX]] <= lru[1][addr[`INDEX]]) lru[3][addr[`INDEX]] <= lru[3][addr[`INDEX]] + 1;
                    lru[1][addr[`INDEX]] = 2'b00;
                end

                else if(valid[2][addr[`INDEX]] && (tag[2][addr[`INDEX]] == addr[`TAG])) 
                begin
                    word_out = {WRD_WIDTH{1'bz}};
                    byte_out = {BYTE{1'bz}};
                    dirty[2][addr[`INDEX]] <= 1'b1;
                    data[2][addr[`INDEX]][(addr[`BOFFSET]*WRD_WIDTH)+:WRD_WIDTH] <= data_wr;

                    // update age registers
                    if(lru[1][addr[`INDEX]] <= lru[2][addr[`INDEX]]) lru[1][addr[`INDEX]] <= lru[1][addr[`INDEX]] + 1;
                    if(lru[0][addr[`INDEX]] <= lru[2][addr[`INDEX]]) lru[0][addr[`INDEX]] <= lru[0][addr[`INDEX]] + 1;
                    if(lru[3][addr[`INDEX]] <= lru[2][addr[`INDEX]]) lru[3][addr[`INDEX]] <= lru[3][addr[`INDEX]] + 1;
                    lru[2][addr[`INDEX]] = 2'b00;
                end

                else if(valid[3][addr[`INDEX]] && (tag[3][addr[`INDEX]] == addr[`TAG])) 
                begin
                    word_out = {WRD_WIDTH{1'bz}};
                    byte_out = {BYTE{1'bz}};
                    dirty[3][addr[`INDEX]] <= 1'b1;
                    data[3][addr[`INDEX]][(addr[`BOFFSET]*WRD_WIDTH)+:WRD_WIDTH] <= data_wr;

                    // update age registers
                    if(lru[1][addr[`INDEX]] <= lru[3][addr[`INDEX]]) lru[1][addr[`INDEX]] <= lru[1][addr[`INDEX]] + 1;
                    if(lru[2][addr[`INDEX]] <= lru[3][addr[`INDEX]]) lru[2][addr[`INDEX]] <= lru[2][addr[`INDEX]] + 1;
                    if(lru[0][addr[`INDEX]] <= lru[3][addr[`INDEX]]) lru[0][addr[`INDEX]] <= lru[0][addr[`INDEX]] + 1;
                    lru[3][addr[`INDEX]] = 2'b00;
                end
            end

            EVICT : begin 
                mem_addr <= addr;
                mem_rd_en <= 1'b1;
                
                // write-back 
                if(valid[0][addr[`INDEX]] && (lru[0][addr[`INDEX]] == 2'b11) && (dirty[0][addr[`INDEX]] == 1'b1)) 
                begin 
                    mem_addr <= addr;
                    mem_wr_en <= 1'b1;
                    mem_wr_blk <= data[0][addr[`INDEX]];
                end

                else if(valid[1][addr[`INDEX]] && (lru[1][addr[`INDEX]] == 2'b11) && (dirty[1][addr[`INDEX]] == 1'b1)) 
                begin 
                    mem_addr <= addr;
                    mem_wr_en <= 1'b1;
                    mem_wr_blk <= data[1][addr[`INDEX]];
                end

                else if(valid[2][addr[`INDEX]] && (lru[2][addr[`INDEX]] == 2'b11) && (dirty[2][addr[`INDEX]] == 1'b1)) 
                begin 
                    mem_addr <= addr;
                    mem_wr_en <= 1'b1;
                    mem_wr_blk <= data[2][addr[`INDEX]];
                end

                else if(valid[3][addr[`INDEX]] && (lru[3][addr[`INDEX]] == 2'b11) && (dirty[3][addr[`INDEX]] == 1'b1)) 
                begin 
                    mem_addr <= addr;
                    mem_wr_en <= 1'b1;
                    mem_wr_blk <= data[3][addr[`INDEX]];
                end
            end

            RD_MISS: begin 
                //mem_rd_en <= 1'b1;
                //mem_addr <= addr;
                word_out <= mem_rd_blk[(addr[`BOFFSET]*WRD_WIDTH)+:WRD_WIDTH];
                byte_out <= mem_rd_blk[(addr[`BOFFSET]*WRD_WIDTH)+(addr[`WOFFSET]*BYTE) +: BYTE];

                if(~valid[0][addr[`INDEX]] || (lru[0][addr[`INDEX]] == 2'b11))
                begin
                    $display("HERE BITCH");
                    data[0][addr[`INDEX]] <= mem_rd_blk;
                    tag[0][addr[`INDEX]] <= addr[`TAG];
                    dirty[0][addr[`INDEX]] <= 1'b0;
                    valid[0][addr[`INDEX]] <= 1'b1;
                end
                
                else if(~valid[1][addr[`INDEX]] || (lru[1][addr[`INDEX]] == 2'b11))
                begin
                    data[1][addr[`INDEX]] <= mem_rd_blk;
                    tag[1][addr[`INDEX]] <= addr[`TAG];
                    dirty[1][addr[`INDEX]] <= 1'b0;
                    valid[1][addr[`INDEX]] <= 1'b1;
                end

                else if(~valid[2][addr[`INDEX]] || (lru[2][addr[`INDEX]] == 2'b11))
                begin
                    data[2][addr[`INDEX]] <= mem_rd_blk;
                    tag[2][addr[`INDEX]] <= addr[`TAG];
                    dirty[2][addr[`INDEX]] <= 1'b0;
                    valid[2][addr[`INDEX]] <= 1'b1;
                end

                else if(~valid[3][addr[`INDEX]] || (lru[3][addr[`INDEX]] == 2'b11))
                begin
                    data[3][addr[`INDEX]] <= mem_rd_blk;
                    tag[3][addr[`INDEX]] <= addr[`TAG];
                    dirty[3][addr[`INDEX]] <= 1'b0;
                    valid[3][addr[`INDEX]] <= 1'b1;
                end
            end

            WR_MISS : begin 
                word_out = {WRD_WIDTH{1'bz}};
                byte_out = {BYTE{1'bz}};

                if(~valid[0][addr[`INDEX]] || (lru[0][addr[`INDEX]] == 2'b11))
                begin
                    data[0][addr[`INDEX]] <= data_wr;
                    tag[0][addr[`INDEX]] <= addr[`TAG];
                    dirty[0][addr[`INDEX]] <= 1'b1;
                    valid[0][addr[`INDEX]] <= 1'b1;
                end

                else if(~valid[1][addr[`INDEX]] || (lru[1][addr[`INDEX]] == 2'b11))
                begin
                    data[1][addr[`INDEX]] <= data_wr;
                    tag[1][addr[`INDEX]] <= addr[`TAG];
                    dirty[1][addr[`INDEX]] <= 1'b1;
                    valid[1][addr[`INDEX]] <= 1'b1;
                end

                else if(~valid[2][addr[`INDEX]] || (lru[2][addr[`INDEX]] == 2'b11))
                begin
                    data[2][addr[`INDEX]] <= data_wr;
                    tag[2][addr[`INDEX]] <= addr[`TAG];
                    dirty[2][addr[`INDEX]] <= 1'b1;
                    valid[2][addr[`INDEX]] <= 1'b1;
                end

                else if(~valid[3][addr[`INDEX]] || (lru[3][addr[`INDEX]] == 2'b11))
                begin
                    data[3][addr[`INDEX]] <= data_wr;
                    tag[3][addr[`INDEX]] <= addr[`TAG];
                    dirty[3][addr[`INDEX]] <= 1'b1;
                    valid[3][addr[`INDEX]] <= 1'b1;
                end
            end
        endcase
    end

endmodule

src/cache_tb.sv
`timescale 1ns/1ns
`include "macros.sv"
`include "cache_data.sv"
`include "mem.sv"

module cache_tb;

    localparam CLK_PERIOD = 100,
               CLK_CYCLES = 10,
               RST_PULSE  = 25;

    reg                  clk, rst_n;
    
    reg [PA_WIDTH-1:0]   addr;
    reg [WRD_WIDTH-1:0]  data_wr;
    
    reg                  rd_en, wr_en;
    
    //memory control outputs
    wire [BLK_WIDTH-1:0] mem_rd_blk;
    reg [PA_WIDTH-1:0]   mem_addr;
    reg                  mem_rd_en, mem_wr_en;
    reg [BLK_WIDTH-1:0]  mem_wr_blk;

    reg                  hit;
    reg [WRD_WIDTH-1:0]  word_out;
    reg [BYTE-1:0]       byte_out;

    //cache signals
    // reg                  cache_mem_wr_en, cache_mem_rd_en;
    // reg [BLK_WIDTH-1:0]  cache_mem_wr_blk;
    // reg [PA_WIDTH-1:0]   cache_mem_addr;

    cache_data CACHE_DUT(
        .clk        (clk), 
        .rst_n      (rst_n),
        .rd_en      (rd_en),
        .wr_en      (wr_en),
        .addr       (addr),
        .data_wr    (data_wr),

        .mem_rd_blk (mem_rd_blk),
        .mem_addr   (mem_addr),
        .mem_rd_en  (mem_rd_en),
        .mem_wr_en  (mem_wr_en),
        .mem_wr_blk (mem_wr_blk),
                            
        .hit        (hit),
        .word_out   (word_out),
        .byte_out   (byte_out)
    );

    mem MEM_DUT(
        .clk     (clk),
        .addr    (mem_addr),
        .rd_en   (mem_rd_en),
        .wr_en   (mem_wr_en),
        .wr_data (mem_wr_blk),
        .rd_data (mem_rd_blk)
    );

    initial begin 
        $dumpfile("cache_data.vcd");
        $dumpvars(0, cache_tb);
    end

    initial begin 
        clk = 1'b1;
        repeat(CLK_CYCLES*2) #(CLK_PERIOD / 2) clk = ~clk;
    end

    initial begin 
        // mem_wr_en = 1'b0;
        // mem_rd_en = 1'b0;
        // rst_n = 1'b0;
        // #(RST_PULSE);
        // rst_n = 1'b1;
        // mem_rd_en = 1'b1;
        // #(CLK_PERIOD-RST_PULSE);
        // mem_addr <= 32'h00;
        // #(CLK_PERIOD);
        // mem_addr <= mem_addr + 32'h40;
        // #(CLK_PERIOD);
        // mem_addr <= mem_addr + 32'h40;

        // #(CLK_PERIOD);
        // mem_addr <= mem_addr + 32'h40;

        // #(CLK_PERIOD);

        rd_en <= 1'b1;
        wr_en <= 1'b0;
        addr <= 32'h00;
        #(CLK_CYCLES);
        #(CLK_CYCLES);
        #(CLK_CYCLES);
        
        #(CLK_CYCLES);
        #(CLK_CYCLES);
        #(CLK_CYCLES);
    end

endmodule

src/cache_data.vcd
$date
	Fri May 31 01:38:11 2024
$end
$version
	Icarus Verilog
$end
$timescale
	1ns
$end
$scope module cache_tb $end
$var wire 32 ! word_out [31:0] $end
$var wire 1 " mem_wr_en $end
$var wire 512 # mem_wr_blk [511:0] $end
$var wire 1 $ mem_rd_en $end
$var wire 512 % mem_rd_blk [511:0] $end
$var wire 32 & mem_addr [31:0] $end
$var wire 1 ' hit $end
$var wire 8 ( byte_out [7:0] $end
$var parameter 32 ) CLK_CYCLES $end
$var parameter 32 * CLK_PERIOD $end
$var parameter 32 + RST_PULSE $end
$var reg 32 , addr [31:0] $end
$var reg 1 - clk $end
$var reg 32 . data_wr [31:0] $end
$var reg 1 / rd_en $end
$var reg 1 0 rst_n $end
$var reg 1 1 wr_en $end
$scope module CACHE_DUT $end
$var wire 32 2 addr [31:0] $end
$var wire 1 - clk $end
$var wire 32 3 data_wr [31:0] $end
$var wire 1 / rd_en $end
$var wire 1 0 rst_n $end
$var wire 1 1 wr_en $end
$var wire 32 4 word_out [31:0] $end
$var wire 1 " mem_wr_en $end
$var wire 512 5 mem_wr_blk [511:0] $end
$var wire 1 $ mem_rd_en $end
$var wire 512 6 mem_rd_blk [511:0] $end
$var wire 32 7 mem_addr [31:0] $end
$var wire 1 ' hit $end
$var wire 8 8 byte_out [7:0] $end
$var integer 32 9 i [31:0] $end
$var integer 32 : j [31:0] $end
$scope module CACHE_CNTRL $end
$var wire 32 ; addr [31:0] $end
$var wire 1 - clk $end
$var wire 32 < data_wr [31:0] $end
$var wire 1 ' hit $end
$var wire 1 / rd_en $end
$var wire 1 0 rst_n $end
$var wire 1 1 wr_en $end
$var wire 512 = mem_rd_blk [511:0] $end
$var parameter 3 > EVICT $end
$var parameter 3 ? IDLE $end
$var parameter 3 @ RD_HIT $end
$var parameter 3 A RD_MISS $end
$var parameter 3 B WR_HIT $end
$var parameter 3 C WR_MISS $end
$var reg 8 D byte_out [7:0] $end
$var reg 32 E mem_addr [31:0] $end
$var reg 1 $ mem_rd_en $end
$var reg 512 F mem_wr_blk [511:0] $end
$var reg 1 " mem_wr_en $end
$var reg 3 G next [2:0] $end
$var reg 1 H rd_m $end
$var reg 3 I state [2:0] $end
$var reg 32 J word_out [31:0] $end
$var reg 1 K wr_m $end
$upscope $end
$upscope $end
$scope module MEM_DUT $end
$var wire 32 L addr [31:0] $end
$var wire 1 - clk $end
$var wire 1 $ rd_en $end
$var wire 512 M wr_data [511:0] $end
$var wire 1 " wr_en $end
$var parameter 32 N BYTES_PER_WORD $end
$var parameter 42 O DEPTH $end
$var parameter 32 P INIT $end
$var parameter 32 Q NSEED_BLK $end
$var parameter 32 R SEED $end
$var parameter 32 S WIDTH $end
$var parameter 32 T WORDS_PER_BLOCK $end
$var reg 512 U rd_data [511:0] $end
$var integer 32 V byte_idx [31:0] $end
$var integer 32 W i [31:0] $end
$var integer 32 X j [31:0] $end
$var integer 32 Y word_idx [31:0] $end
$upscope $end
$upscope $end
$enddefinitions $end
$comment Show the parameter values. $end
$dumpall
b10000 T
b1000 S
b1 R
b100 Q
b0 P
b10000000000 O
b100 N
b100 C
b11 B
b10 A
b1 @
b0 ?
b101 >
b11001 +
b1100100 *
b1010 )
$end
#0
$dumpvars
bx Y
b1000000 X
b100000000 W
bx V
bx U
bx M
bx L
xK
bx J
bx I
xH
bx G
bx F
bx E
bx D
bx =
bx <
b0 ;
b10000000 :
b100 9
bx 8
bx 7
bx 6
bx 5
bx 4
bx 3
b0 2
01
x0
1/
bx .
1-
b0 ,
bx (
x'
bx &
bx %
x$
bx #
x"
bx !
$end
#50
0-
#100
b10000000 :
b100 9
1-
#150
0-
#200
b10000000 :
b100 9
1-
#250
0-
#300
b10000000 :
b100 9
1-
#350
0-
#400
b10000000 :
b100 9
1-
#450
0-
#500
b10000000 :
b100 9
1-
#550
0-
#600
b10000000 :
b100 9
1-
#650
0-
#700
b10000000 :
b100 9
1-
#750
0-
#800
b10000000 :
b100 9
1-
#850
0-
#900
b10000000 :
b100 9
1-
#950
0-
#1000
b10000000 :
b100 9
1-
