src/macros.sv
/*
* Author:            Sorin Besleaga
* Last modification: 29.05.24
* Status:            finished
*/

//byte-addressable
`ifndef _macros_h
`define _macros_h
    //Phisical Address:
    `define WOFFSET 1:0   // word offset
    `define BOFFSET 5:2   // block offset
    `define INDEX   12:6  // index slice
    `define TAG     31:13 // tag slice

    localparam TST_SIZE  = (1<<12);

    //Cache defines:
    localparam BYTE      = 8;       // 1 B =  8 bits
    localparam SIZE      = (1<<18); // total size of cache data size in bits
    localparam NWAYS     = 4;       // number of set associetivity
    localparam NSETS     = 128;     // number of sets in cache
    localparam BLK_WIDTH = 512;     // size of the block in bits
    localparam PA_WIDTH  = 32;      // width of physical address and  in bits
    localparam WRD_WIDTH = 32;      // width of a word in bits


    localparam IDX_WIDTH = 7;       // 128 sets (1 set = 4 blocks)
    localparam TAG_WIDTH = 19;
    localparam BO_WIDTH  = 4;       // 16 words/block
    localparam WO_WIDTH  = 2;       // 4 B/word

`endif

src/mem.sv
/*
* Author:            Sorin Besleaga
* Last modification: 30.05.24
* Status:            finished
*/

`include "macros.sv"
//treb de definit aici operatiile pe memorie
//Un aray de byte-uri

module mem #(
    parameter DEPTH     = (1<<15),   // 32KB
    parameter WIDTH     = BYTE,
    parameter INIT      = 0,         // if 1, resets all the memory
    parameter SEED      = 1,
    parameter NSEED_BLK = 512
)
(
    input  wire                 clk,

    input  wire [PA_WIDTH-1:0]  addr,

    input  wire                 rd_en,
    input  wire                 wr_en,

    input  wire [BLK_WIDTH-1:0] wr_data,
    output reg  [BLK_WIDTH-1:0] rd_data
);

    reg [WIDTH-1:0] MM [0:DEPTH-1];
    integer i, j;

    initial begin 
        if(INIT)
        begin
            for(i = 0; i < DEPTH; i = i+1)
                MM[i] = {WIDTH{1'b0}};
        end
        
        if(SEED) 
        begin 
            for(i = 0; i < (BLK_WIDTH/BYTE)*NSEED_BLK; i = i+32'h40)
            begin 
                for (j = 0; j < (BLK_WIDTH/BYTE); j = j + 1) begin
                    MM[i+j] = {8'h0f + (i-j*i), 8'hf0 - (i*j+j)};
                    
                    //$display("MM[%d] = %h", i+j, MM[i+j]);
                end
            end

        end
    end


    // Calculate the number of words per block
    localparam WORDS_PER_BLOCK = BLK_WIDTH / WRD_WIDTH;
    localparam BYTES_PER_WORD = WRD_WIDTH / WIDTH;

    integer word_idx, byte_idx;

    // Read from Main Memory
    always @(*) begin
        if (rd_en) begin
            for (word_idx = 0; word_idx < WORDS_PER_BLOCK; word_idx = word_idx + 1) begin
                for (byte_idx = 0; byte_idx < BYTES_PER_WORD; byte_idx = byte_idx + 1) begin
                    rd_data[(word_idx * WRD_WIDTH) + (byte_idx * WIDTH) +: WIDTH] = MM[addr + (word_idx * BYTES_PER_WORD) + byte_idx];
                end
            end
            
        end
    end

    // Write to Main Memory
    always @(*) begin
        if (wr_en) begin
            for (word_idx = 0; word_idx < WORDS_PER_BLOCK; word_idx = word_idx + 1) begin
                for (byte_idx = 0; byte_idx < BYTES_PER_WORD; byte_idx = byte_idx + 1) begin
                    MM[addr + (word_idx * BYTES_PER_WORD) + byte_idx] = wr_data[(word_idx * WRD_WIDTH) + (byte_idx * WIDTH) +: WIDTH];
                    
                    //It assures that when it is read and write enables at the same time, it will provide at rd_data the value that come in wr_data
                    if(rd_en)
                        rd_data[(word_idx * WRD_WIDTH) + (byte_idx * WIDTH) +: WIDTH] = wr_data[(word_idx * WRD_WIDTH) + (byte_idx * WIDTH) +: WIDTH];
                    // $display("(addr: %d)(index_addr: %d) %h",addr,addr + (word_idx * BYTES_PER_WORD) + byte_idx, MM[addr + (word_idx * BYTES_PER_WORD) + byte_idx]);
                end
            end
            // $display("\n");
        end
    end

endmodule

src/cache_data.sv
/*
* Author:            Sorin Besleaga
* Last modification: 31.05.24
* Status:            finished
*/

/*
* Specs:
*       Associativity level: 4   way
*       Cache data size:     32  KiB
*       Block size:          64  B/block
*       Number of sets:      128 sets
*       Word size:           4   B/word
*       Words per block:     16  words/block
*       Memory alignment:    Little-Endian (bytes in words and words in blocks are stored in little-endian)
                                            LSB bits are stored at top of Main Memory, and so in cache blocks
*/

`include "macros.sv"

module cache_data
(
    input  wire                  clk, rst_n,
    
    input  wire [PA_WIDTH-1:0]   addr,         // addr from CPU
    input  wire [WRD_WIDTH-1:0]  data_wr,      // data from CPU (store instruction) / data to write 
    
    input  wire                  rd_en,        // 1 if load instr
    input  wire                  wr_en,        // 1 if store instr
    
    //memory control outputs
    input  wire [BLK_WIDTH-1:0]  mem_rd_blk,
    output reg  [PA_WIDTH-1:0]   mem_addr,
    output reg                   mem_rd_en,
    output reg                   mem_wr_en,    // 1 if writing to memory
    output reg [BLK_WIDTH-1:0]   mem_wr_blk,   // data from cache to memory

    //cache outputs
    output reg                   hit,          // 1 if hit, 0 if miss
    output reg  [WRD_WIDTH-1:0]  word_out,     // data from cache to CPU
    output reg  [BYTE-1:0]       byte_out,     // byte that is extracted from word

    output reg                   rdy           // says when it is ready to get new address
);

    // Define all ways
    reg                  valid [0:NWAYS-1][0:NSETS-1];
    reg                  dirty [0:NWAYS-1][0:NSETS-1];
    reg [1:0]            lru   [0:NWAYS-1][0:NSETS-1];
    reg [TAG_WIDTH-1:0]  tag   [0:NWAYS-1][0:NSETS-1];
    reg [BLK_WIDTH-1:0]  data  [0:NWAYS-1][0:NSETS-1];

    // Init to 0 all
    integer i, j, k;
    initial begin 
        for(i = 0; i < NWAYS; i = i + 1) 
        begin
            for(j = 0; j < NSETS; j = j + 1) 
            begin 
                valid[i][j] = 1'b0;
                dirty[i][j] = 1'b0;
                lru  [i][j] = 2'b00;
            end
        end
    end

    // always @* begin 
    //     for(i = 0; i < NWAYS; i = i + 1) 
    //     begin
    //         for(j = 0; j < NSETS; j = j + 1) 
    //         begin 
    //             $display("valid = %h dirty = %h lru = %h", valid[i][j], dirty[i][j], lru[i][j]);
    //         end
    //         $display("=======\n");
    //     end
    // end

    // start of actual FSM

    // state parameters
    localparam IDLE       = 3'b000;
    localparam RD_HIT     = 3'b001;
    localparam RD_MISS    = 3'b010;
    localparam WR_HIT     = 3'b011;
    localparam WR_MISS    = 3'b100;
    localparam EVICT      = 3'b101;
         
    // state registers
    reg[2:0] state, next;
    reg rd_m, wr_m;

    //change states
    always @(posedge clk, negedge rst_n) begin 
        if(!rst_n) state <= IDLE;
        else       state <= next;
    end

    // set next state
    always @(*) begin 
        next = state;
        case(state)
            IDLE : begin   
                if((~rd_en && ~wr_en)||
                    (rd_en && wr_en))  next = IDLE;
                else if(rd_en && hit)  next = RD_HIT;
                else if(wr_en && hit)  next = WR_HIT;
                else if(rd_en && ~hit) 
                begin 
                                       next = EVICT;
                                       rd_m = 1'b1;
                                       wr_m = 1'b0;
                end
                else if(wr_en && ~hit)
                begin 
                                       next = EVICT;
                                       rd_m = 1'b0;
                                       wr_m = 1'b1;
                end
            end

            EVICT : begin
                    if(wr_m)           next = WR_MISS;
                    if(rd_m)           next = RD_MISS;
            end

            RD_HIT,
            WR_HIT,
            RD_MISS, 
            WR_MISS :                  next = IDLE;              
        endcase
    end

    always @* begin 
        $display("ADDR: %b(%d)ten (%h)hex SET: %d",addr, addr,addr, addr[`INDEX]);
        for(i = 0; i < NWAYS; i = i+1)
        begin 
            $display("(block idx: %d)(BO: %d) (WO: %d) valid = %b lru = %b dirty = %b",i, addr[`BOFFSET], addr[`WOFFSET], valid[i][addr[`INDEX]], lru[i][addr[`INDEX]], dirty[i][addr[`INDEX]]);
        end
        $display("==================\n");
    end

    // trigger signals based on next state
    always @(posedge clk, negedge rst_n) 
    begin 
        case(next)
            IDLE: begin 
                hit <= ((valid[0][addr[`INDEX]] && (tag[0][addr[`INDEX]] == addr[`TAG]))
                      ||(valid[1][addr[`INDEX]] && (tag[1][addr[`INDEX]] == addr[`TAG]))
                      ||(valid[2][addr[`INDEX]] && (tag[2][addr[`INDEX]] == addr[`TAG]))
                      ||(valid[3][addr[`INDEX]] && (tag[3][addr[`INDEX]] == addr[`TAG])));

                {wr_m, rd_m, mem_wr_en, mem_rd_en, rdy} <= 5'b00000;

                word_out <= {WRD_WIDTH{1'bz}};
                byte_out <= {WRD_WIDTH{1'bz}};
            end

            RD_HIT: begin 
                rdy <= 1'b1;
                begin : rd_hit_loop
                    for(i = 0; i < NWAYS; i = i+1)
                    begin 
                        if(valid[i][addr[`INDEX]] && (tag[i][addr[`INDEX]] == addr[`TAG])) 
                        begin
                            word_out <= data[i][addr[`INDEX]][(addr[`BOFFSET]*WRD_WIDTH)+:WRD_WIDTH];
                            byte_out <= data[i][addr[`INDEX]][(addr[`BOFFSET]*WRD_WIDTH)+(addr[`WOFFSET]*BYTE) +: BYTE];

                            // update age registers
                            for(j = 0; j < NWAYS; j = j+1)
                                if((i!=j) && (lru[j][addr[`INDEX]] <= lru[i][addr[`INDEX]]) && valid[j][addr[`INDEX]])
                                    lru[j][addr[`INDEX]] <= lru[j][addr[`INDEX]] + 2'b01;
                            lru[i][addr[`INDEX]] <= 2'b00;

                            disable rd_hit_loop;
                        end
                    end
                end
            end

            WR_HIT : begin 
                 // i_th way
                rdy <= 1'b1;
                begin : wr_hit_loop
                    for(i = 0; i < NWAYS; i = i+1)
                    begin 
                        if(valid[i][addr[`INDEX]] && (tag[i][addr[`INDEX]] == addr[`TAG])) 
                        begin
                            // for store instr there is no output/byte word
                            word_out = {WRD_WIDTH{1'bz}};
                            byte_out = {BYTE{1'bz}};
                            // mark as dirty block
                            dirty[i][addr[`INDEX]] <= 1'b1;
                            // overwrite data info from cache's block
                            data[i][addr[`INDEX]][(addr[`BOFFSET]*WRD_WIDTH)+:WRD_WIDTH] <= data_wr;

                            for(j = 0; j < NWAYS; j = j+1)
                                if((i!=j) && lru[j][addr[`INDEX]] <= lru[i][addr[`INDEX]] && valid[j][addr[`INDEX]])
                                    lru[j][addr[`INDEX]] <= lru[j][addr[`INDEX]] + 1;
                            lru[i][addr[`INDEX]] <= 2'b00;

                            disable wr_hit_loop;
                        end
                    end
                end
            end

            EVICT : begin 
                mem_addr <= addr;
                mem_rd_en <= 1'b1;

                begin : evict_loop 
                    for(i = 0; i < NWAYS; i=i+1)
                    begin 
                        if(valid[i][addr[`INDEX]]  && (dirty[i][addr[`INDEX]] == 1'b1)) //&& (lru[i][addr[`INDEX]] == 2'b11)
                        begin 
                            mem_wr_en <= 1'b1;
                            mem_wr_blk <= data[i][addr[`INDEX]];
                            
                            disable evict_loop;
                        end
                    end
                end
            end

            RD_MISS: begin 
                rdy <= 1'b1;
                mem_wr_en <= 1'b0;
                word_out <= mem_rd_blk[(addr[`BOFFSET]*WRD_WIDTH)+:WRD_WIDTH];
                byte_out <= mem_rd_blk[(addr[`BOFFSET]*WRD_WIDTH)+(addr[`WOFFSET]*BYTE) +: BYTE];

                begin : rd_miss_loop
                    for(i = 0; i < NWAYS; i = i+1)
                    begin 
                        if(~valid[i][addr[`INDEX]] || (lru[i][addr[`INDEX]] == 2'b11))
                        begin
                            data[i][addr[`INDEX]] <= mem_rd_blk;
                            tag[i][addr[`INDEX]] <= addr[`TAG];
                            dirty[i][addr[`INDEX]] <= 1'b0;
                            valid[i][addr[`INDEX]] <= 1'b1;
                            disable rd_miss_loop;
                        end
                    end
                end
            end

            WR_MISS : begin 
                rdy <= 1'b1;
                mem_rd_en <= 1'b0;
                word_out = {WRD_WIDTH{1'bz}};
                byte_out = {BYTE{1'bz}};

                begin : wr_miss_loop
                    for(i = 0; i < NWAYS; i = i+1)
                    begin 
                        if(~valid[i][addr[`INDEX]] || (lru[i][addr[`INDEX]] == 2'b11))
                        begin
                            data[i][addr[`INDEX]] <= data_wr;
                            tag[i][addr[`INDEX]] <= addr[`TAG];
                            dirty[i][addr[`INDEX]] <= 1'b1;
                            valid[i][addr[`INDEX]] <= 1'b1;

                            disable wr_miss_loop;
                        end
                    end
                end
            end
        endcase
    end

endmodule

src/cache_tb.sv
`timescale 1ns/1ns
`include "macros.sv"
`include "cache_data.sv"
`include "mem.sv"

module cache_tb;

    localparam           CLK_PERIOD = 100,
                         CLK_CYCLES = 20,
                         RST_PULSE  = 25;

    reg                  clk, rst_n;
    
    reg [PA_WIDTH-1:0]   addr;
    reg [WRD_WIDTH-1:0]  data_wr;
    
    reg                  rd_en, wr_en;
    
    //memory control outputs
    wire[BLK_WIDTH-1:0]  mem_rd_blk;
    reg [PA_WIDTH-1:0]   mem_addr;
    reg                  mem_rd_en, mem_wr_en;
    reg [BLK_WIDTH-1:0]  mem_wr_blk;

    //cache output
    reg                  hit;
    reg [WRD_WIDTH-1:0]  word_out;
    reg [BYTE-1:0]       byte_out;

    reg                  rdy;

    cache_data CACHE_DUT(
        .clk        (clk), 
        .rst_n      (rst_n),
        .rd_en      (rd_en),
        .wr_en      (wr_en),
        .addr       (addr),
        .data_wr    (data_wr),

        .mem_rd_blk (mem_rd_blk),
        .mem_addr   (mem_addr),
        .mem_rd_en  (mem_rd_en),
        .mem_wr_en  (mem_wr_en),
        .mem_wr_blk (mem_wr_blk),
                            
        .hit        (hit),
        .word_out   (word_out),
        .byte_out   (byte_out),

        .rdy        (rdy)
    );

    mem MEM_DUT(
        .clk     (clk),
        .addr    (mem_addr),
        .rd_en   (mem_rd_en),
        .wr_en   (mem_wr_en),
        .wr_data (mem_wr_blk),
        .rd_data (mem_rd_blk)
    );

    initial begin 
        $dumpfile("cache_data.vcd");
        $dumpvars(0, cache_tb);
    end

    initial begin 
        clk = 1'b1;
        forever #(CLK_PERIOD / 2) clk = ~clk;
    end
    reg[31:0] i;
    initial begin  
        //reset
        rst_n = 1'b0;
        rd_en = 1'b1;
        wr_en = 1'b0;
        //read miss
        addr = 32'h00;//8
        #(RST_PULSE);
        rst_n = 1'b1;
        @(posedge rdy);


        // // //read hit
        // // addr <= 32'h15;
        // // @(posedge rdy);
        // // //next word
        // // //read hit
        // // addr <= addr + 32'h04;
        // // @(posedge rdy);

        // // //write miss
        // // wr_en <= 1'b1;
        // // rd_en <= 1'b0;
        // // data_wr <= 32'hfafa_fafa;
        // // addr <= 32'h20d5; //8405
        // // @(posedge rdy);

        // // //write hit
        // // data_wr <= 32'hdada_dada;
        // // addr <= 32'h20d5;
        // // @(posedge rdy);

        // // //read hit
        // // wr_en <= 1'b0;
        // // rd_en <= 1'b1;
        // // addr <= 32'h20d5;
        // // @(posedge rdy);

        //read miss or write miss to replace dirty blocks to MM
        //set 0
        addr = 32'h2000;
        @(posedge rdy);
        addr = 32'h4000;
        @(posedge rdy);
        addr = 32'h6000;
        @(posedge rdy);

        //write hit + lru increment
        rd_en = 1'b0;
        wr_en = 1'b1;
        addr = 32'h4000;
        data_wr = 32'hfafa_fafa;
        @(posedge rdy);

        //read hit 
        rd_en = 1'b1;
        wr_en = 1'b0;
        @(posedge rdy);

        //read/write miss + replacement
        addr = 32'h8000;
        @(posedge rdy);


        // //set1
        // addr = 32'h0040;
        // @(posedge rdy);
        // addr = 32'h2040;
        // @(posedge rdy);
        // addr = 32'h4040;
        // @(posedge rdy);
        // addr = 32'h6040;
        // @(posedge rdy);


        // //read hits to increase lru
        // addr = 32'h2000;
        // @(posedge rdy);
        // //read hits next word
        // addr = addr + 32'h4;
        // @(posedge rdy);

        // addr = addr + 32'h40 - 32'h4;
        // @(posedge rdy);

        // //write to 32'h2040 with incremented lru
        // //write hit
        // rd_en = 1'b0;
        // wr_en = 1'b1;
        // data_wr = 32'hfafa_fafa;
        // addr = 32'h2040;
        // @(posedge rdy);

        // //read hit
        // rd_en = 1'b1;
        // wr_en = 1'b0;
        // addr = 32'h00;
        // @(posedge rdy);



        @(posedge clk);
        $finish();
        
    end

endmodule

src/cache_data.vcd
$date
	Fri May 31 20:13:41 2024
$end
$version
	Icarus Verilog
$end
$timescale
	1ns
$end
$scope module cache_tb $end
$var wire 32 ! word_out [31:0] $end
$var wire 1 " rdy $end
$var wire 1 # mem_wr_en $end
$var wire 512 $ mem_wr_blk [511:0] $end
$var wire 1 % mem_rd_en $end
$var wire 512 & mem_rd_blk [511:0] $end
$var wire 32 ' mem_addr [31:0] $end
$var wire 1 ( hit $end
$var wire 8 ) byte_out [7:0] $end
$var parameter 32 * CLK_CYCLES $end
$var parameter 32 + CLK_PERIOD $end
$var parameter 32 , RST_PULSE $end
$var reg 32 - addr [31:0] $end
$var reg 1 . clk $end
$var reg 32 / data_wr [31:0] $end
$var reg 1 0 rd_en $end
$var reg 1 1 rst_n $end
$var reg 1 2 wr_en $end
$scope module CACHE_DUT $end
$var wire 32 3 addr [31:0] $end
$var wire 1 . clk $end
$var wire 32 4 data_wr [31:0] $end
$var wire 1 0 rd_en $end
$var wire 1 1 rst_n $end
$var wire 1 2 wr_en $end
$var wire 512 5 mem_rd_blk [511:0] $end
$var parameter 3 6 EVICT $end
$var parameter 3 7 IDLE $end
$var parameter 3 8 RD_HIT $end
$var parameter 3 9 RD_MISS $end
$var parameter 3 : WR_HIT $end
$var parameter 3 ; WR_MISS $end
$var reg 8 < byte_out [7:0] $end
$var reg 1 ( hit $end
$var reg 32 = mem_addr [31:0] $end
$var reg 1 % mem_rd_en $end
$var reg 512 > mem_wr_blk [511:0] $end
$var reg 1 # mem_wr_en $end
$var reg 3 ? next [2:0] $end
$var reg 1 @ rd_m $end
$var reg 1 " rdy $end
$var reg 3 A state [2:0] $end
$var reg 32 B word_out [31:0] $end
$var reg 1 C wr_m $end
$var integer 32 D i [31:0] $end
$var integer 32 E j [31:0] $end
$scope begin evict_loop $end
$upscope $end
$scope begin rd_hit_loop $end
$upscope $end
$scope begin rd_miss_loop $end
$upscope $end
$scope begin wr_hit_loop $end
$upscope $end
$scope begin wr_miss_loop $end
$upscope $end
$upscope $end
$scope module MEM_DUT $end
$var wire 32 F addr [31:0] $end
$var wire 1 . clk $end
$var wire 1 % rd_en $end
$var wire 512 G wr_data [511:0] $end
$var wire 1 # wr_en $end
$var parameter 32 H BYTES_PER_WORD $end
$var parameter 47 I DEPTH $end
$var parameter 32 J INIT $end
$var parameter 32 K NSEED_BLK $end
$var parameter 32 L SEED $end
$var parameter 32 M WIDTH $end
$var parameter 32 N WORDS_PER_BLOCK $end
$var reg 512 O rd_data [511:0] $end
$var integer 32 P byte_idx [31:0] $end
$var integer 32 Q i [31:0] $end
$var integer 32 R j [31:0] $end
$var integer 32 S word_idx [31:0] $end
$upscope $end
$upscope $end
$enddefinitions $end
$comment Show the parameter values. $end
$dumpall
b10000 N
b1000 M
b1 L
b1000000000 K
b0 J
b1000000000000000 I
b100 H
b100 ;
b11 :
b10 9
b1 8
b0 7
b101 6
b11001 ,
b1100100 +
b10100 *
$end
#0
$dumpvars
bx S
b1000000 R
b1000000000000000 Q
bx P
bx O
bx G
bx F
b10000000 E
b100 D
xC
bx B
b0 A
x@
b0 ?
bx >
bx =
bx <
bx 5
bx 4
b0 3
02
01
10
bx /
1.
b0 -
bx )
x(
bx '
bx &
x%
bx $
x#
x"
bx !
$end
#25
11
#50
0.
#100
b101 ?
bz )
bz <
bz !
bz B
0C
1@
0#
0%
0"
0(
1.
#150
0.
#200
b10 ?
b10110001101100101011001110110100101101011011011010110111101110001011100110111010101110111011110010111101101111101011111111000000110000011100001011000011110001001100010111000110110001111100100011001001110010101100101111001100110011011100111011001111110100001101000111010010110100111101010011010101110101101101011111011000110110011101101011011011110111001101110111011110110111111110000011100001111000101110001111100100111001011110011011100111111010001110100111101010111010111110110011101101111011101110111111110000 &
b10110001101100101011001110110100101101011011011010110111101110001011100110111010101110111011110010111101101111101011111111000000110000011100001011000011110001001100010111000110110001111100100011001001110010101100101111001100110011011100111011001111110100001101000111010010110100111101010011010101110101101101011111011000110110011101101011011011110111001101110111011110110111111110000011100001111000101110001111100100111001011110011011100111111010001110100111101010111010111110110011101101111011101110111111110000 5
b10110001101100101011001110110100101101011011011010110111101110001011100110111010101110111011110010111101101111101011111111000000110000011100001011000011110001001100010111000110110001111100100011001001110010101100101111001100110011011100111011001111110100001101000111010010110100111101010011010101110101101101011111011000110110011101101011011011110111001101110111011110110111111110000011100001111000101110001111100100111001011110011011100111111010001110100111101010111010111110110011101101111011101110111111110000 O
b100 P
b10000 S
b101 A
1%
b0 '
b0 =
b0 F
b100 D
1.
#250
0.
#300
b0 ?
b10000000000000 -
b10000000000000 3
b10 A
b11110000 )
b11110000 <
b11101101111011101110111111110000 !
b11101101111011101110111111110000 B
1"
b100 D
1.
#350
0.
#400
b101 ?
b0 A
bz )
bz <
bz !
bz B
1@
0%
0"
1.
#450
0.
#500
b100 P
b10000 S
b10 ?
1%
b10000000000000 '
b10000000000000 =
b10000000000000 F
b101 A
b100 D
1.
#550
0.
#600
b0 ?
b100000000000000 -
b100000000000000 3
b10 A
b11110000 )
b11110000 <
b11101101111011101110111111110000 !
b11101101111011101110111111110000 B
1"
b100 D
1.
#650
0.
#700
b101 ?
b0 A
bz )
bz <
bz !
bz B
1@
0%
0"
1.
#750
0.
#800
b100 P
b10000 S
b10 ?
1%
b100000000000000 '
b100000000000000 =
b100000000000000 F
b101 A
b100 D
1.
#850
0.
#900
b0 ?
b110000000000000 -
b110000000000000 3
b10 A
b11110000 )
b11110000 <
b11101101111011101110111111110000 !
b11101101111011101110111111110000 B
1"
b100 D
1.
#950
0.
#1000
b101 ?
b0 A
bz )
bz <
bz !
bz B
1@
0%
0"
1.
#1050
0.
#1100
b100 P
b10000 S
b10 ?
1%
b110000000000000 '
b110000000000000 =
b110000000000000 F
b101 A
b100 D
1.
#1150
0.
#1200
b0 ?
b11111010111110101111101011111010 /
b11111010111110101111101011111010 4
b100000000000000 -
b100000000000000 3
12
00
b10 A
b11110000 )
b11110000 <
b11101101111011101110111111110000 !
b11101101111011101110111111110000 B
1"
b100 D
1.
#1250
0.
#1300
b11 ?
b0 A
bz )
bz <
bz !
bz B
0@
0%
0"
1(
1.
#1350
0.
#1400
02
10
b0 ?
1"
b11 A
b100 E
b100 D
1.
#1450
0.
#1500
b1 ?
b0 A
0"
1.
#1550
0.
#1600
b1000000000000000 -
b1000000000000000 3
b0 ?
b11111010 )
b11111010 <
b11111010111110101111101011111010 !
b11111010111110101111101011111010 B
1"
b1 A
b100 E
b100 D
1.
#1650
0.
#1700
1@
b101 ?
b0 A
bz )
bz <
bz !
bz B
0"
0(
1.
#1750
0.
#1800
b10110001101100101011001110110100101101011011011010110111101110001011100110111010101110111011110010111101101111101011111111000000110000011100001011000011110001001100010111000110110001111100100011001001110010101100101111001100110011011100111011001111110100001101000111010010110100111101010011010101110101101101011111011000110110011101101011011011110111001101110111011110110111111110000011100001111000101110001111100100111001011110011011100111111010001110100111101010111010111110110011111010111110101111101011111010 &
b10110001101100101011001110110100101101011011011010110111101110001011100110111010101110111011110010111101101111101011111111000000110000011100001011000011110001001100010111000110110001111100100011001001110010101100101111001100110011011100111011001111110100001101000111010010110100111101010011010101110101101101011111011000110110011101101011011011110111001101110111011110110111111110000011100001111000101110001111100100111001011110011011100111111010001110100111101010111010111110110011111010111110101111101011111010 5
b10110001101100101011001110110100101101011011011010110111101110001011100110111010101110111011110010111101101111101011111111000000110000011100001011000011110001001100010111000110110001111100100011001001110010101100101111001100110011011100111011001111110100001101000111010010110100111101010011010101110101101101011111011000110110011101101011011011110111001101110111011110110111111110000011100001111000101110001111100100111001011110011011100111111010001110100111101010111010111110110011111010111110101111101011111010 O
b100 P
b10000 S
b10 ?
b10110001101100101011001110110100101101011011011010110111101110001011100110111010101110111011110010111101101111101011111111000000110000011100001011000011110001001100010111000110110001111100100011001001110010101100101111001100110011011100111011001111110100001101000111010010110100111101010011010101110101101101011111011000110110011101101011011011110111001101110111011110110111111110000011100001111000101110001111100100111001011110011011100111111010001110100111101010111010111110110011111010111110101111101011111010 $
b10110001101100101011001110110100101101011011011010110111101110001011100110111010101110111011110010111101101111101011111111000000110000011100001011000011110001001100010111000110110001111100100011001001110010101100101111001100110011011100111011001111110100001101000111010010110100111101010011010101110101101101011111011000110110011101101011011011110111001101110111011110110111111110000011100001111000101110001111100100111001011110011011100111111010001110100111101010111010111110110011111010111110101111101011111010 >
b10110001101100101011001110110100101101011011011010110111101110001011100110111010101110111011110010111101101111101011111111000000110000011100001011000011110001001100010111000110110001111100100011001001110010101100101111001100110011011100111011001111110100001101000111010010110100111101010011010101110101101101011111011000110110011101101011011011110111001101110111011110110111111110000011100001111000101110001111100100111001011110011011100111111010001110100111101010111010111110110011111010111110101111101011111010 G
1#
1%
b1000000000000000 '
b1000000000000000 =
b1000000000000000 F
b101 A
b10 D
1.
#1850
0.
#1900
b0 ?
b10 A
b11111010 )
b11111010 <
b11111010111110101111101011111010 !
b11111010111110101111101011111010 B
0#
1"
b100 D
1.
#1950
0.
#2000
b101 ?
b0 A
bz )
bz <
bz !
bz B
1@
0%
0"
1.
